is_isbn/__init__.py
is_isbn/is_isbn.py
is_isbn-0.1.0.dist-info/AUTHORS.rst
is_isbn-0.1.0.dist-info/LICENSE
is_isbn-0.1.0.dist-info/METADATA
is_isbn-0.1.0.dist-info/WHEEL
is_isbn-0.1.0.dist-info/top_level.txt
is_isbn-0.1.0.dist-info/RECORD
