Metadata-Version: 2.1
Name: is-isbn
Version: 0.1.0
Summary: Checks if the provided string is valid ISBN.
Home-page: https://github.com/khimsh/is_isbn
Author: Ia Khimshiashvili
Author-email: i.khimsh@gmail.com
License: MIT license
Keywords: is_isbn
Platform: UNKNOWN
Classifier: Development Status :: 2 - Pre-Alpha
Classifier: Intended Audience :: Developers
Classifier: License :: OSI Approved :: MIT License
Classifier: Natural Language :: English
Classifier: Programming Language :: Python :: 3
Classifier: Programming Language :: Python :: 3.4
Classifier: Programming Language :: Python :: 3.5
Classifier: Programming Language :: Python :: 3.6
Classifier: Programming Language :: Python :: 3.7
